Workbook

Sheet LFB1
A1: Supplier | B1: NAME | C1: Company Code | D1: Trading partner | E1: Created On | F1: Created by | G1: Payment Block | H1: Terms of Payment | I1: Check Double Invoice
A2: 1000 | B2: =VLOOKUP(A2,'LFA1'!A:C,3,FALSE) -> CYBEX GmbH | C2: CZ02 | D2: =VLOOKUP(A2,'LFA1'!A:J,10,0) -> CBGM | E2: 43136 | F2: HEMPELJU | H2: Z106
A3: 1000 | B3: =VLOOKUP(A3,'LFA1'!A:C,3,FALSE) -> CYBEX GmbH | C3: US02 | D3: =VLOOKUP(A3,'LFA1'!A:J,10,0) -> CBGM | E3: 44403 | F3: SCHULZEST | H3: Z104
A4: 1003 | B4: =VLOOKUP(A4,'LFA1'!A:C,3,FALSE) -> Columbus Trading Partners | C4: CH02 | D4: =VLOOKUP(A4,'LFA1'!A:J,10,0) -> CTPE | E4: 43923 | F4: VIDDAD01 | H4: 0001
A5: 1003 | B5: =VLOOKUP(A5,'LFA1'!A:C,3,FALSE) -> Columbus Trading Partners | C5: GB02 | D5: =VLOOKUP(A5,'LFA1'!A:J,10,0) -> CTPE | E5: 44195 | F5: YUSMOH01
A6: 1003 | B6: =VLOOKUP(A6,'LFA1'!A:C,3,FALSE) -> Columbus Trading Partners | C6: NO02 | D6: =VLOOKUP(A6,'LFA1'!A:J,10,0) -> CTPE | E6: 44095 | F6: YUSMOH01 | H6: 0001
A7: 1009 | B7: =VLOOKUP(A7,'LFA1'!A:C,3,FALSE) -> GB GmbH | C7: US02 | D7: =VLOOKUP(A7,'LFA1'!A:J,10,0) -> GBGM | E7: 44420 | F7: GB_FFUS_MM01 | H7: Z104
A8: 1014 | B8: =VLOOKUP(A8,'LFA1'!A:C,3,FALSE) -> Goodbaby (Hong Kong) Limited | C8: CZ01 | D8: =VLOOKUP(A8,'LFA1'!A:J,10,0) -> GBHK | E8: 43167 | F8: HEMPELJU
A9: 1014 | B9: =VLOOKUP(A9,'LFA1'!A:C,3,FALSE) -> Goodbaby (Hong Kong) Limited | C9: DE08 | D9: =VLOOKUP(A9,'LFA1'!A:J,10,0) -> GBHK | E9: 43406 | F9: HEMPELJU
A10: 1015 | B10: =VLOOKUP(A10,'LFA1'!A:C,3,FALSE) -> Columbus Trading - Partners | C10: CA02 | D10: =VLOOKUP(A10,'LFA1'!A:J,10,0) -> CBUS | E10: 44784 | F10: GURWAD01
A11: 1015 | B11: =VLOOKUP(A11,'LFA1'!A:C,3,FALSE) -> Columbus Trading - Partners | C11: FR70 | D11: =VLOOKUP(A11,'LFA1'!A:J,10,0) -> CBUS | E11: 45777 | F11: FF_EX_SC_BU
A12: 1015 | B12: =VLOOKUP(A12,'LFA1'!A:C,3,FALSE) -> Columbus Trading - Partners | C12: US70 | D12: =VLOOKUP(A12,'LFA1'!A:J,10,0) -> CBUS | E12: 45779 | F12: FF_EX_SC_BU
A13: 1018 | B13: =VLOOKUP(A13,'LFA1'!A:C,3,FALSE) -> Evenflo Company,Inc. | C13: CA02 | D13: =VLOOKUP(A13,'LFA1'!A:J,10,0) -> EFCD | E13: 44903 | F13: BIACIM01
A14: 1018 | B14: =VLOOKUP(A14,'LFA1'!A:C,3,FALSE) -> Evenflo Company,Inc. | C14: CZ02 | D14: =VLOOKUP(A14,'LFA1'!A:J,10,0) -> EFCD | E14: 43978 | F14: NIKBRI01
A15: 1024 | B15: =VLOOKUP(A15,'LFA1'!A:C,3,FALSE) -> Eqo Testing and Certification Co. L | C15: DE02 | D15: =VLOOKUP(A15,'LFA1'!A:J,10,0) -> EQTC | E15: 44678 | F15: SCHULZEST | H15: Z104
A16: 1028 | B16: =VLOOKUP(A16,'LFA1'!A:C,3,FALSE) -> Goodbaby (China) | C16: DE02 | D16: =VLOOKUP(A16,'LFA1'!A:J,10,0) -> GRCN | E16: 43073 | F16: HORNDO
A17: 1030 | B17: =VLOOKUP(A17,'LFA1'!A:C,3,FALSE) -> Columbus Trading-Partners Japan Lim | C17: DE01 | D17: =VLOOKUP(A17,'LFA1'!A:J,10,0) -> CBJP | E17: 43137 | F17: HORNDO | H17: Z107
A18: 1030 | B18: =VLOOKUP(A18,'LFA1'!A:C,3,FALSE) -> Columbus Trading-Partners Japan Lim | C18: DE02 | D18: =VLOOKUP(A18,'LFA1'!A:J,10,0) -> CBJP | E18: 43467 | F18: SABBRE01 | H18: Z107
A19: 1030 | B19: =VLOOKUP(A19,'LFA1'!A:C,3,FALSE) -> Columbus Trading-Partners Japan Lim | C19: DE08 | D19: =VLOOKUP(A19,'LFA1'!A:J,10,0) -> CBJP | E19: 43467 | F19: SABBRE01 | H19: Z107
A20: 1030 | B20: =VLOOKUP(A20,'LFA1'!A:C,3,FALSE) -> Columbus Trading-Partners Japan Lim | C20: DE09 | D20: =VLOOKUP(A20,'LFA1'!A:J,10,0) -> CBJP | E20: 44139 | F20: THICAV01 | H20: Z107
A21: 1031 | B21: =VLOOKUP(A21,'LFA1'!A:C,3,FALSE) -> Rollplay GmbH | C21: DE03 | D21: =VLOOKUP(A21,'LFA1'!A:J,10,0) -> RPGM | E21: 43248 | F21: SIMONAL
A22: 1037 | B22: =VLOOKUP(A22,'LFA1'!A:C,3,FALSE) -> Columbus Trading Partners | C22: US02 | D22: =VLOOKUP(A22,'LFA1'!A:J,10,0) | E22: 44407 | F22: GB_FFUS_MM02
A23: 1038 | B23: =VLOOKUP(A23,'LFA1'!A:C,3,FALSE) -> Piqua | C23: US02 | D23: =VLOOKUP(A23,'LFA1'!A:J,10,0) | E23: 44618 | F23: US_FFID_MM01
A24: 1040 | B24: =VLOOKUP(A24,'LFA1'!A:C,3,FALSE) -> Columbus Trading Partners Gmbh & Co | C24: DE02 | D24: =VLOOKUP(A24,'LFA1'!A:J,10,0) -> CTPE | E24: 43245 | F24: BUIQU
A25: 1040 | B25: =VLOOKUP(A25,'LFA1'!A:C,3,FALSE) -> Columbus Trading Partners Gmbh & Co | C25: DE08 | D25: =VLOOKUP(A25,'LFA1'!A:J,10,0) -> CTPE | E25: 46113 | F25: DENWAS01
A26: 1060 | B26: =VLOOKUP(A26,'LFA1'!A:C,3,FALSE) -> 1060 - FIEGE (Cybex) | C26: DE02 | D26: =VLOOKUP(A26,'LFA1'!A:J,10,0) | E26: 44263 | F26: LALMOH01 | H26: Z106
A27: 1070 | B27: =VLOOKUP(A27,'LFA1'!A:C,3,FALSE) -> 1070 - FIEGE (GB) | C27: DE02 | D27: =VLOOKUP(A27,'LFA1'!A:J,10,0) | E27: 44263 | F27: LALMOH01 | H27: Z106
A28: 1110 | B28: =VLOOKUP(A28,'LFA1'!A:C,3,FALSE) -> Columbus Trading Partner IMEA (FZE) | C28: AE02 | D28: =VLOOKUP(A28,'LFA1'!A:J,10,0) -> CTPF | E28: 45967 | F28: NUWNAN01
A29: 1110 | B29: =VLOOKUP(A29,'LFA1'!A:C,3,FALSE) -> Columbus Trading Partner IMEA (FZE) | C29: AE04 | D29: =VLOOKUP(A29,'LFA1'!A:J,10,0) -> CTPF | E29: 45908 | F29: FF_EX_FI_BU
A30: 1110 | B30: =VLOOKUP(A30,'LFA1'!A:C,3,FALSE) -> Columbus Trading Partner IMEA (FZE) | C30: AE09 | D30: =VLOOKUP(A30,'LFA1'!A:J,10,0) -> CTPF | E30: 45987 | F30: FF_IN_FI_BU
A31: 1900 | B31: =VLOOKUP(A31,'LFA1'!A:C,3,FALSE) -> Goodbaby Czech Republic s.r.o | C31: CZ01 | D31: =VLOOKUP(A31,'LFA1'!A:J,10,0) | E31: 42664 | F31: RFC_GBP
A32: 2000 | B32: =VLOOKUP(A32,'LFA1'!A:C,3,FALSE) -> CYBEX Retail GmbH | C32: AE02 | D32: =VLOOKUP(A32,'LFA1'!A:J,10,0) -> CBRG | E32: 46017 | F32: SUMELV01
A33: 2000 | B33: =VLOOKUP(A33,'LFA1'!A:C,3,FALSE) -> CYBEX Retail GmbH | C33: AE09 | D33: =VLOOKUP(A33,'LFA1'!A:J,10,0) -> CBRG | E33: 46021 | F33: SUMELV01
A34: 2000 | B34: =VLOOKUP(A34,'LFA1'!A:C,3,FALSE) -> CYBEX Retail GmbH | C34: FR70 | D34: =VLOOKUP(A34,'LFA1'!A:J,10,0) -> CBRG | E34: 45616 | F34: FF_EX_SC_BU | H34: Z059
A35: 2020 | B35: =VLOOKUP(A35,'LFA1'!A:C,3,FALSE) -> CYBEX Retail GmbH | C35: DE09 | D35: =VLOOKUP(A35,'LFA1'!A:J,10,0) -> CBRG | E35: 45125 | F35: GB_FF_INT02
A36: 2030 | B36: =VLOOKUP(A36,'LFA1'!A:C,3,FALSE) -> Cybex Retail Store Paris SAS | C36: FR70 | D36: =VLOOKUP(A36,'LFA1'!A:J,10,0) -> CBRF | E36: 45616 | F36: FF_EX_SC_BU | H36: Z059
A37: 2050 | B37: =VLOOKUP(A37,'LFA1'!A:C,3,FALSE) -> CYBEX Retail Berlin | C37: DE09 | D37: =VLOOKUP(A37,'LFA1'!A:J,10,0) -> CBRG | E37: 45939 | F37: FF_EX_SC_BU
A38: 10000 | B38: =VLOOKUP(A38,'LFA1'!A:C,3,FALSE) -> CYBEX GmbH | C38: AE02 | D38: =VLOOKUP(A38,'LFA1'!A:J,10,0) -> CBGM | E38: 45174 | F38: DENWAS01
A39: 10000 | B39: =VLOOKUP(A39,'LFA1'!A:C,3,FALSE) -> CYBEX GmbH | C39: AE04 | D39: =VLOOKUP(A39,'LFA1'!A:J,10,0) -> CBGM | E39: 46094 | F39: SUMELV01
A40: 10000 | B40: =VLOOKUP(A40,'LFA1'!A:C,3,FALSE) -> CYBEX GmbH | C40: CZ01 | D40: =VLOOKUP(A40,'LFA1'!A:J,10,0) -> CBGM | E40: 42725 | F40: HORNDO
A41: 10000 | B41: =VLOOKUP(A41,'LFA1'!A:C,3,FALSE) -> CYBEX GmbH | C41: DE02 | D41: =VLOOKUP(A41,'LFA1'!A:J,10,0) -> CBGM | E41: 42492 | F41: SCHULZEST
A42: 10000 | B42: =VLOOKUP(A42,'LFA1'!A:C,3,FALSE) -> CYBEX GmbH | C42: DE04 | D42: =VLOOKUP(A42,'LFA1'!A:J,10,0) -> CBGM | E42: 42500 | F42: SCHULZEST
A43: 10000 | B43: =VLOOKUP(A43,'LFA1'!A:C,3,FALSE) -> CYBEX GmbH | C43: DE08 | D43: =VLOOKUP(A43,'LFA1'!A:J,10,0) -> CBGM | E43: 43843 | F43: RIHASU
A44: 10000 | B44: =VLOOKUP(A44,'LFA1'!A:C,3,FALSE) -> CYBEX GmbH | C44: DE09 | D44: =VLOOKUP(A44,'LFA1'!A:J,10,0) -> CBGM | E44: 44160 | F44: RIHASU
A45: 10001 | B45: =VLOOKUP(A45,'LFA1'!A:C,3,FALSE) -> Columbus Trading-Partners GmbH & Co | C45: DE01 | D45: =VLOOKUP(A45,'LFA1'!A:J,10,0) -> CTPE | E45: 42493 | F45: SCHULZEST
A46: 10001 | B46: =VLOOKUP(A46,'LFA1'!A:C,3,FALSE) -> Columbus Trading-Partners GmbH & Co | C46: DE03 | D46: =VLOOKUP(A46,'LFA1'!A:J,10,0) -> CTPE | E46: 42635 | F46: HORNDO
A47: 10001 | B47: =VLOOKUP(A47,'LFA1'!A:C,3,FALSE) -> Columbus Trading-Partners GmbH & Co | C47: DE09 | D47: =VLOOKUP(A47,'LFA1'!A:J,10,0) -> CTPE | E47: 44139 | F47: THICAV01
A48: 10006 | B48: =VLOOKUP(A48,'LFA1'!A:C,3,FALSE) -> Goodbaby (Europe) GmbH & Co. KG | C48: DE04 | D48: =VLOOKUP(A48,'LFA1'!A:J,10,0) -> GEGC | E48: 42500 | F48: SCHULZEST
... A56: 10013 | B56: =VLOOKUP(A56,'LFA1'!A:C,3,FALSE) -> Goodbaby International Holdings Ltd | C56: DE01 | D56: =VLOOKUP(A56,'LFA1'!A:J,10,0) -> GIHL | E56: 43840 | F56: RIHASU
A57: 10013 | B57: =VLOOKUP(A57,'LFA1'!A:C,3,FALSE) -> Goodbaby International Holdings Ltd | C57: DE03 | D57: =VLOOKUP(A57,'LFA1'!A:J,10,0) -> GIHL | E57: 42502 | F57: SCHULZEST | H57: Z104
A58: 10013 | B58: =VLOOKUP(A58,'LFA1'!A:C,3,FALSE) -> Goodbaby International Holdings Ltd | C58: DE09 | D58: =VLOOKUP(A58,'LFA1'!A:J,10,0) -> GIHL | E58: 44139 | F58: THICAV01
A59: 10014 | B59: =VLOOKUP(A59,'LFA1'!A:C,3,FALSE) -> Goodbaby (Hong Kong) Limited | C59: DE01 | D59: =VLOOKUP(A59,'LFA1'!A:J,10,0) -> GBHK | E59: 42884 | F59: SCHULZEST
A60: 10014 | B60: =VLOOKUP(A60,'LFA1'!A:C,3,FALSE) -> Goodbaby (Hong Kong) Limited | C60: DE03 | D60: =VLOOKUP(A60,'LFA1'!A:J,10,0) -> GBHK | E60: 42558 | F60: SCHULZEST
A61: 10014 | B61: =VLOOKUP(A61,'LFA1'!A:C,3,FALSE) -> Goodbaby (Hong Kong) Limited | C61: DE08 | D61: =VLOOKUP(A61,'LFA1'!A:J,10,0) -> GBHK | E61: 43409 | F61: RIHASU
A62: 10014 | B62: =VLOOKUP(A62,'LFA1'!A:C,3,FALSE) -> Goodbaby (Hong Kong) Limited | C62: DE09 | D62: =VLOOKUP(A62,'LFA1'!A:J,10,0) -> GBHK | E62: 44139 | F62: THICAV01
A63: 10015 | B63: =VLOOKUP(A63,'LFA1'!A:C,3,FALSE) -> Columbus Trading - Partners USA Inc | C63: DE04 | D63: =VLOOKUP(A63,'LFA1'!A:J,10,0) -> CBUS | E63: 42500 | F63: SCHULZEST
A64: 10018 | B64: =VLOOKUP(A64,'LFA1'!A:C,3,FALSE) -> Evenflo Company,Inc. | C64: DE01 | D64: =VLOOKUP(A64,'LFA1'!A:J,10,0) -> EFCD | E64: 42732 | F64: HORNDO
A65: 10018 | B65: =VLOOKUP(A65,'LFA1'!A:C,3,FALSE) -> Evenflo Company,Inc. | C65: DE09 | D65: =VLOOKUP(A65,'LFA1'!A:J,10,0) -> EFCD | E65: 44139 | F65: THICAV01
A66: 10030 | B66: =VLOOKUP(A66,'LFA1'!A:C,3,FALSE) -> Columbus Trading-Partners Japan Lim | C66: DE01 | D66: =VLOOKUP(A66,'LFA1'!A:J,10,0) -> CBJP | E66: 45390 | F66: DENWAS01
A67: 50000 | B67: =VLOOKUP(A67,'LFA1'!A:C,3,FALSE) -> Philipp Raum | C67: DE03 | D67: =VLOOKUP(A67,'LFA1'!A:J,10,0) | E67: 42490 | F67: BUIQU
A68: 50000 | B68: =VLOOKUP(A68,'LFA1'!A:C,3,FALSE) -> Philipp Raum | C68: DE07 | D68: =VLOOKUP(A68,'LFA1'!A:J,10,0) | E68: 42490 | F68: BUIQU
A69: 50001 | B69: =VLOOKUP(A69,'LFA1'!A:C,3,FALSE) -> Dmitrij Brandt | C69: DE03 | D69: =VLOOKUP(A69,'LFA1'!A:J,10,0) | E69: 42490 | F69: BUIQU
... A131: 50066 | B131: =VLOOKUP(A131,'LFA1'!A:C,3,FALSE) -> Annika Jänicke - Corporate Design | C131: DE01 | D131: =VLOOKUP(A131,'LFA1'!A:J,10,0) | E131: 42491 | F131: BUIQU
A132: 50351 | B132: =VLOOKUP(A132,'LFA1'!A:C,3,FALSE) -> Cleide de Sousa Tizzei | C132: DE01 | D132: =VLOOKUP(A132,'LFA1'!A:J,10,0) | E132: 42955 | F132: SCHNEIDERJU | H132: Z152
A133: 50352 | B133: =VLOOKUP(A133,'LFA1'!A:C,3,FALSE) -> Joao Ricardo Gastl | C133: DE01 | D133: =VLOOKUP(A133,'LFA1'!A:J,10,0) | E133: 42961 | F133: SABBRE01 | H133: Z152
A134: 50379 | B134: =VLOOKUP(A134,'LFA1'!A:C,3,FALSE) -> Amelie Schlenk | C134: DE02 | D134: =VLOOKUP(A134,'LFA1'!A:J,10,0) | E134: 43017 | F134: SABBRE01 | H134: Z152
A135: 50519 | B135: =VLOOKUP(A135,'LFA1'!A:C,3,FALSE) -> Moritz Beck | C135: DE01 | D135: =VLOOKUP(A135,'LFA1'!A:J,10,0) | E135: 43445 | F135: SABBRE01 | H135: Z152
A136: 50521 | B136: =VLOOKUP(A136,'LFA1'!A:C,3,FALSE) -> Daisy Wong Ping | C136: DE01 | D136: =VLOOKUP(A136,'LFA1'!A:J,10,0) | E136: 43445 | F136: BENZSA | H136: Z152
A137: 50523 | B137: =VLOOKUP(A137,'LFA1'!A:C,3,FALSE) -> Silke Kroack | C137: DE03 | D137: =VLOOKUP(A137,'LFA1'!A:J,10,0) | E137: 43447 | F137: BENZSA | H137: Z152
A138: 53256 | B138: =VLOOKUP(A138,'LFA1'!A:C,3,FALSE) -> Zsuzsa Szekely-CRM | C138: DE02 | D138: =VLOOKUP(A138,'LFA1'!A:J,10,0) | E138: 44286 | F138: PAUPEL01
A139: 53258 | B139: =VLOOKUP(A139,'LFA1'!A:C,3,FALSE) -> Matteo Cabiola (Liguria) | C139: DE02 | D139: =VLOOKUP(A139,'LFA1'!A:J,10,0) | E139: 44286 | F139: PAUPEL01
A140: 53260 | B140: =VLOOKUP(A140,'LFA1'!A:C,3,FALSE) -> Veronika Radlinger-CRM | C140: DE02 | D140: =VLOOKUP(A140,'LFA1'!A:J,10,0) | E140: 44286 | F140: PAUPEL01
A141: 53262 | B141: =VLOOKUP(A141,'LFA1'!A:C,3,FALSE) -> Matteo Cabiola | C141: DE02 | D141: =VLOOKUP(A141,'LFA1'!A:J,10,0) | E141: 44286 | F141: PAUPEL01
A142: 53266 | B142: =VLOOKUP(A142,'LFA1'!A:C,3,FALSE) -> Jana Kovarova-CRM | C142: DE02 | D142: =VLOOKUP(A142,'LFA1'!A:J,10,0) | E142: 44286 | F142: PAUPEL01
A143: 53268 | B143: =VLOOKUP(A143,'LFA1'!A:C,3,FALSE) -> Kamil Bojanovsky-CRM | C143: DE02 | D143: =VLOOKUP(A143,'LFA1'!A:J,10,0) | E143: 44286 | F143: PAUPEL01
A144: 53272 | B144: =VLOOKUP(A144,'LFA1'!A:C,3,FALSE) -> Tomas Madej | C144: DE02 | D144: =VLOOKUP(A144,'LFA1'!A:J,10,0) | E144: 44292 | F144: PAUPEL01
A145: 53276 | B145: =VLOOKUP(A145,'LFA1'!A:C,3,FALSE) -> Marek Adam | C145: DE02 | D145: =VLOOKUP(A145,'LFA1'!A:J,10,0) | E145: 44293 | F145: PAUPEL01
A146: 53279 | B146: =VLOOKUP(A146,'LFA1'!A:C,3,FALSE) -> Michaela Benesova | C146: DE02 | D146: =VLOOKUP(A146,'LFA1'!A:J,10,0) | E146: 44293 | F146: PAUPEL01
A147: 53282 | B147: =VLOOKUP(A147,'LFA1'!A:C,3,FALSE) -> Dana Krasova | C147: DE02 | D147: =VLOOKUP(A147,'LFA1'!A:J,10,0) | E147: 44293 | F147: PAUPEL01
A148: 53284 | B148: =VLOOKUP(A148,'LFA1'!A:C,3,FALSE) -> Kushan Singh-CRM | C148: DE01 | D148: =VLOOKUP(A148,'LFA1'!A:J,10,0) | E148: 44294 | F148: PAUPEL01
A149: 53286 | B149: =VLOOKUP(A149,'LFA1'!A:C,3,FALSE) -> Diego Alonso Sobrino | C149: DE02 | D149: =VLOOKUP(A149,'LFA1'!A:J,10,0) | E149: 44294 | F149: PAUPEL01
... A382: 54005 | B382: =VLOOKUP(A382,'LFA1'!A:C,3,FALSE) -> Michael Görsch (BeLux) | C382: DE02 | D382: =VLOOKUP(A382,'LFA1'!A:J,10,0) | E382: 44377 | F382: VIDDAD01
A383: 54007 | B383: =VLOOKUP(A383,'LFA1'!A:C,3,FALSE) -> Carolina Aguiar | C383: DE02 | D383: =VLOOKUP(A383,'LFA1'!A:J,10,0) | E383: 44377 | F383: VIDDAD01 | G383: A
A384: 54009 | B384: =VLOOKUP(A384,'LFA1'!A:C,3,FALSE) -> Roman Ziem | C384: DE02 | D384: =VLOOKUP(A384,'LFA1'!A:J,10,0) | E384: 44377 | F384: VIDDAD01
A385: 54011 | B385: =VLOOKUP(A385,'LFA1'!A:C,3,FALSE) -> CRM Bosnia Herzegowina | C385: DE02 | D385: =VLOOKUP(A385,'LFA1'!A:J,10,0) | E385: 44377 | F385: VIDDAD01
A386: 54016 | B386: =VLOOKUP(A386,'LFA1'!A:C,3,FALSE) -> CRM Albania NEW Sales rep | C386: DE02 | D386: =VLOOKUP(A386,'LFA1'!A:J,10,0) | E386: 44377 | F386: VIDDAD01
A387: 54019 | B387: =VLOOKUP(A387,'LFA1'!A:C,3,FALSE) -> CRM Montenegro | C387: DE02 | D387: =VLOOKUP(A387,'LFA1'!A:J,10,0) | E387: 44377 | F387: VIDDAD01
A388: 54022 | B388: =VLOOKUP(A388,'LFA1'!A:C,3,FALSE) -> Michael Höfner | C388: DE02 | D388: =VLOOKUP(A388,'LFA1'!A:J,10,0) | E388: 44377 | F388: VIDDAD01
A389: 54025 | B389: =VLOOKUP(A389,'LFA1'!A:C,3,FALSE) -> Paulo Pela | C389: DE02 | D389: =VLOOKUP(A389,'LFA1'!A:J,10,0) | E389: 44377 | F389: VIDDAD01
A390: 54027 | B390: =VLOOKUP(A390,'LFA1'!A:C,3,FALSE) -> Adrien Barbarossa | C390: DE02 | D390: =VLOOKUP(A390,'LFA1'!A:J,10,0) | E390: 44377 | F390: VIDDAD01
A391: 54031 | B391: =VLOOKUP(A391,'LFA1'!A:C,3,FALSE) -> Quentin Surmont | C391: DE02 | D391: =VLOOKUP(A391,'LFA1'!A:J,10,0) | E391: 44377 | F391: VIDDAD01
A392: 54033 | B392: =VLOOKUP(A392,'LFA1'!A:C,3,FALSE) -> Selma Busovaca | C392: DE02 | D392: =VLOOKUP(A392,'LFA1'!A:J,10,0) | E392: 44377 | F392: VIDDAD01
A393: 54060 | B393: =VLOOKUP(A393,'LFA1'!A:C,3,FALSE) -> Steffen Dahinten (KAM FH) (AT) | C393: DE02 | D393: =VLOOKUP(A393,'LFA1'!A:J,10,0) | E393: 44386 | F393: NAVKHA01
A394: 54073 | B394: =VLOOKUP(A394,'LFA1'!A:C,3,FALSE) -> Eduardo Chousal-CRM | C394: DE02 | D394: =VLOOKUP(A394,'LFA1'!A:J,10,0) | E394: 44393 | F394: PAUPEL01
A395: 54103 | B395: =VLOOKUP(A395,'LFA1'!A:C,3,FALSE) -> CRM Croatia | C395: DE02 | D395: =VLOOKUP(A395,'LFA1'!A:J,10,0) | E395: 44411 | F395: PAUPEL01
... A423: 54287 | B423: =VLOOKUP(A423,'LFA1'!A:C,3,FALSE) -> Denis Zwezich | C423: DE02 | D423: =VLOOKUP(A423,'LFA1'!A:J,10,0) | E423: 44531 | F423: PAUPEL01
A424: 54290 | B424: =VLOOKUP(A424,'LFA1'!A:C,3,FALSE) -> Ladislav Capek | C424: DE01 | D424: =VLOOKUP(A424,'LFA1'!A:J,10,0) | E424: 44533 | F424: SCHULZEST | H424: Z152
A425: 54299 | B425: =VLOOKUP(A425,'LFA1'!A:C,3,FALSE) -> Preetham Jakkenahalli Basavaraj | C425: DE02 | D425: =VLOOKUP(A425,'LFA1'!A:J,10,0) | E425: 44539 | F425: PAUPEL01
A426: 54303 | B426: =VLOOKUP(A426,'LFA1'!A:C,3,FALSE) -> Jiri Hejduk | C426: DE02 | D426: =VLOOKUP(A426,'LFA1'!A:J,10,0) | E426: 44540 | F426: PAUPEL01
A427: 54319 | B427: =VLOOKUP(A427,'LFA1'!A:C,3,FALSE) -> Michela Rocco | C427: DE02 | D427: =VLOOKUP(A427,'LFA1'!A:J,10,0) | E427: 44574 | F427: PAUPEL01
...

Sheet LFA1
A1: Supplier | B1: Country/Region Key | C1: Name | D1: Name 2 | E1: Name 3 | F1: Name 4 | G1: City | H1: District | I1: PO Box | J1: Trading Partner No.
A2: 1000 | B2: DE | C2: CYBEX GmbH | G2: Bayreuth | J2: CBGM
A3: 1003 | B3: DE | C3: Columbus Trading Partners | G3: Bayreuth | J3: CTPE
A4: 1009 | B4: DE | C4: GB GmbH | G4: Bayreuth | J4: GBGM
A5: 1014 | B5: HK | C5: Goodbaby (Hong Kong) Limited | G5: San Po Kong, Kowloon | J5: GBHK
A6: 1015 | B6: US | C6: Columbus Trading - Partners | D6: USA Inc. | G6: Boston | H6: Suffolk | J6: CBUS
A7: 1018 | B7: US | C7: Evenflo Company,Inc. | G7: Miamisburg | J7: EFCD
A8: 1024 | B8: CN | C8: Eqo Testing and Certification Co. L | G8: Kunshan | H8: Lujia Town | J8: EQTC
A9: 1028 | B9: CN | C9: Goodbaby (China) | D9: Retail & Service Company | G9: KUNSHAN CITY | J9: GRCN
A10: 1030 | B10: JP | C10: Columbus Trading-Partners Japan Lim | G10: Tokyo | J10: CBJP
A11: 1031 | B11: DE | C11: Rollplay GmbH | G11: Nürnberg | J11: RPGM
A12: 1037 | B12: CN | C12: Columbus Trading Partners | D12: Plant Cust/Vend for 1020 | G12: Shanghai
A13: 1038 | B13: US | C13: Piqua | D13: Plant Cust/Vend for 1031 | G13: Piqua | H13: Miami
A14: 1040 | B14: DE | C14: Columbus Trading Partners Gmbh & Co | D14: c/o Pfenning Logistics GmbH | G14: Monsheim | J14: CTPE
A15: 1060 | B15: CN | C15: 1060 - FIEGE (Cybex) | D15: Fiege Logistics SIP Co., Ltd. | G15: Shanghai
A16: 1070 | B16: CN | C16: 1070 - FIEGE (GB) | D16: Fiege Logistics SIP Co., Ltd. | G16: Shanghai
A17: 1110 | B17: AE | C17: Columbus Trading Partner IMEA (FZE) | G17: Dubai | J17: CTPF
A18: 1900 | B18: CZ | C18: Goodbaby Czech Republic s.r.o
A19: 2000 | B19: DE | C19: CYBEX Retail GmbH | G19: Bayreuth | J19: CBRG
A20: 2020 | B20: NL | C20: CYBEX Retail GmbH | G20: Amsterdam | J20: CBRG
A21: 2030 | B21: FR | C21: Cybex Retail Store Paris SAS | G21: Paris | J21: CBRF
A22: 2050 | B22: DE | C22: CYBEX Retail Berlin | G22: Berlin | J22: CBRG
A23: 10000 | B23: DE | C23: CYBEX GmbH | G23: Bayreuth | J23: CBGM
A24: 10001 | B24: DE | C24: Columbus Trading-Partners GmbH & Co | G24: Bayreuth | J24: CTPE
A25: 10006 | B25: DE | C25: Goodbaby (Europe) GmbH & Co. KG | G25: Bayreuth | J25: GEGC
A26: 10008 | B26: HK | C26: Cybex Industrial Ltd. | G26: Hong Kong | J26: CBHK
A27: 10011 | B27: DE | C27: Columbus Holding GmbH | G27: Bayreuth | J27: CBCH
A28: 10013 | B28: HK | C28: Goodbaby International Holdings Ltd | G28: Hong Kong | J28: GIHL
A29: 10014 | B29: HK | C29: Goodbaby (Hong Kong) Limited | G29: Kunshan City | J29: GBHK
A30: 10015 | B30: US | C30: Columbus Trading - Partners USA Inc | G30: Kennesaw | J30: CBUS
... A32: 10030 | B32: JP | C32: Columbus Trading-Partners Japan Lim | G32: Tokyo | J32: CBJP
A33: 50000 | B33: DE | C33: Philipp Raum | G33: Bayreuth
A34: 50001 | B34: DE | C34: Dmitrij Brandt | G34: Bayreuth
A35: 50002 | B35: DE | C35: Tobias Salzmann | G35: Bayreuth
A36: 50003 | B36: DE | C36: Christian Aschenbrenner | G36: Bayreuth
A37: 50005 | B37: IT | C37: Francesca San Giorgio | G37: Bayreuth
A38: 50006 | B38: DE | C38: Mark Dostal - Key Account Manager G | G38: Bayreuth
A39: 50007 | B39: DE | C39: Herbert Becker - Verkaufsleiter Fac | G39: Bayreuth
A40: 50009 | B40: DE | C40: André Biedenbacher, AD Norddeutschl | G40: Bayreuth
A41: 50010 | B41: DE | C41: Daniel Harrington | G41: Bayreuth
A42: 50012 | B42: DE | C42: Edyta Powell | D42: geb. Strzalkowska | G42: Bayreuth
A43: 50013 | B43: DE | C43: Melanie Müller - Chief Editor, Mark | G43: Bayreuth
A44: 50014 | B44: DE | C44: Franz Karl, Marketing Berlin | G44: Bayreuth
A45: 50015 | B45: DE | C45: Sebastian Knebelkamp - Director Tra | G45: Bayreuth
A46: 50016 | B46: DE | C46: Florian Scharff | G46: Bayreuth
A47: 50017 | B47: DE | C47: Lisa Schmitt - Specialist Internati | G47: Bayreuth
A48: 50018 | B48: DE | C48: Thomas Müller - Specialist Crash Te | G48: Bayreuth
A49: 50019 | B49: DE | C49: Josefine Jarzombek | G49: Bayreuth
A50: 50020 | B50: DE | C50: Hannah Buchwald - Graphic Designer | G50: Bayreuth
A51: 50022 | B51: DE | C51: Anke Wenk - Senior Manager Fashion | G51: Bayreuth
A52: 50024 | B52: DE | C52: Anita Schnaus | G52: Bayreuth
A53: 50025 | B53: DE | C53: Melissa V. Duzer | G53: Bayreuth
A54: 50026 | B54: PL | C54: Anna Tomczuk | D54: Manager Marketing Poland | G54: Bayreuth
A55: 50027 | B55: DE | C55: Carina Svensson - Senior PR Manager | G55: Bayreuth
A56: 50028 | B56: DE | C56: Ruben Baumann - Vice President Inte | G56: Bayreuth
A57: 50029 | B57: IT | C57: Barbara Venturini - Junior Sales Ma | G57: Bayreuth
A58: 50030 | B58: DE | C58: Peter Amrein - Export Manager | G58: Bayreuth
A59: 50031 | B59: DE | C59: Johnny Røn - Director Quality Manag | G59: Bayreuth
A60: 50032 | B60: NL | C60: Harrie De Beer | G60: Hoor
A61: 50033 | B61: DE | C61: Johanna Samou - Deputy Director Fas | G61: Bayreuth
A62: 50034 | B62: BE | C62: Sociaal Secretariaat Securex | G62: Bayreuth
A63: 50035 | B63: DE | C63: Alexander Höller - Project Manager | G63: Bayreuth
A64: 50036 | B64: AT | C64: Manfred Resch, Product Development | G64: Bayreuth
A65: 50037 | B65: DE | C65: Petra Napier | G65: Bayreuth
A66: 50038 | B66: DE | C66: Bofang Li - Manager Sales & Marketi | G66: Bayreuth
... A360: 54175 | B360: DE | C360: Christoph Kemptner | G360: Bayreuth
A361: 54178 | B361: US | C361: Andre Jean-Louis | G361: Boston | H361: Suffolk
A362: 54183 | B362: DE | C362: Martina Grsak | G362: Bayreuth
A363: 54186 | B363: IT | C363: Arianna di Antonio | G363: Vicenza
A364: 54188 | B364: DE | C364: Maximilian Stocks (MENA) | G364: Bayreuth
A365: 54196 | B365: DE | C365: Martin Rost | G365: Bayreuth
A366: 54199 | B366: US | C366: Livingston Sinclair | G366: Canton | H366: Norfolk
A367: 54208 | B367: DK | C367: Mads Norskov Holst | G367: Viby
A368: 54215 | B368: DE | C368: Samir Abu Alfa | G368: Bayreuth
A369: 54218 | B369: DE | C369: Sezgin Gyuney | G369: Bayreuth
A370: 54221 | B370: DE | C370: Thomas Teufel | G370: Bayreuth
A371: 54225 | B371: DE | C371: Urs Hessenauer | G371: Bayreuth
A372: 54227 | B372: DE | C372: Urs Hessenauer (AT) | G372: Bayreuth
A373: 54233 | B373: DE | C373: Sebastiaan Heemskerk | G373: Bayreuth
A374: 54236 | B374: DE | C374: Johannes Retunzew | G374: Bayreuth
A375: 54253 | B375: DE | C375: Sven Gubitz | G375: Bayreuth
A376: 54260 | B376: DE | C376: Daniel Quauck | G376: Bayreuth
A377: 54271 | B377: DE | C377: Matej Pus | G377: Bayreuth
A378: 54273 | B378: DE | C378: Matej Pus (Slovenia) | G378: Bayreuth
... A404: 54473 | B404: DE | C404: Place Holder | G404: Bayreuth
A405: 54475 | B405: US | C405: Erin Simon | G405: Canton | H405: Norfolk
A406: 54477 | B406: US | C406: Julie Haley | G406: Canton | H406: Norfolk
A407: 54479 | B407: US | C407: Livingston Sinclair (US) | G407: Canton | H407: Norfolk
A408: 54481 | B408: US | C408: Patsy Pilcher | G408: Canton | H408: Norfolk
A409: 54483 | B409: US | C409: Lawrance Norman (US) | G409: Canton | H409: Norfolk
A410: 54485 | B410: US | C410: Fernanda Vergara (MX) | G410: Canton | H410: Norfolk
A411: 54487 | B411: US | C411: Daniella Romano | G411: Canton | H411: Norfolk
A412: 54489 | B412: US | C412: Ramon Melo (US) | G412: Canton | H412: Norfolk
A413: 54491 | B413: US | C413: Felicia Pandola (US) | G413: Canton | H413: Norfolk
A414: 54493 | B414: US | C414: Jackie Rosen | G414: Canton | H414: Norfolk
A415: 54495 | B415: US | C415: Denae Benjamin (US) | G415: Canton | H415: Norfolk
A416: 54497 | B416: US | C416: Cheyenne Rivera (US) | G416: Canton | H416: Norfolk
... A420: 54505 | B420: US | C420: Olivia Roll | G420: Canton | H420: Norfolk
A421: 54524 | B421: DE | C421: Jonas Pettersson | G421: Bayreuth
A422: 54536 | B422: DE | C422: Tereza Nachtmanova | G422: Bayreuth
...
